demo_helpingai/HelpingAI.py
demo_helpingai/__init__.py
demo_helpingai-0.2.dist-info/LICENSE
demo_helpingai-0.2.dist-info/METADATA
demo_helpingai-0.2.dist-info/WHEEL
demo_helpingai-0.2.dist-info/top_level.txt
demo_helpingai-0.2.dist-info/RECORD
